tar_dir_indexer/__init__.py
tar_dir_indexer/tarDirIndexer.py
tar_dir_indexer/version.py
tar_dir_indexer-0.0.3.dist-info/LICENSE
tar_dir_indexer-0.0.3.dist-info/METADATA
tar_dir_indexer-0.0.3.dist-info/WHEEL
tar_dir_indexer-0.0.3.dist-info/top_level.txt
tar_dir_indexer-0.0.3.dist-info/RECORD
