Metadata-Version: 2.1
Name: tar-dir-indexer
Version: 0.0.3
Summary: Indexes directories unraveling tar files within. Also indexes nested tar files.
Home-page: https://github.com/CeadeS/tar_dir_indexer
Author: Martin Hofmann
Author-email: Martin.Hofmann@tu-ilmenau.de
License: BSD-3-Clause License
Platform: UNKNOWN
Classifier: Development Status :: 4 - Beta
Classifier: Intended Audience :: Developers
Classifier: Intended Audience :: Education
Classifier: Intended Audience :: Science/Research
Classifier: License :: OSI Approved :: BSD License
Classifier: Operating System :: POSIX :: Linux
Classifier: Operating System :: Microsoft :: Windows :: Windows 10
Classifier: Programming Language :: Python :: 3
Classifier: Programming Language :: Python :: 3.7
Classifier: Programming Language :: Python :: 3.9
Classifier: Programming Language :: Python :: 3.10
License-File: LICENSE
Requires-Dist: numpy (>=1.17.4)
Requires-Dist: anytree
Requires-Dist: Pillow
Requires-Dist: scikit-image
Requires-Dist: tqdm
Requires-Dist: simplejpeg
